setup.py
./__init__.py
./mysql_versioning.py
./version.py
versioning.egg-info/PKG-INFO
versioning.egg-info/SOURCES.txt
versioning.egg-info/dependency_links.txt
versioning.egg-info/requires.txt
versioning.egg-info/top_level.txt