Metadata-Version: 1.0
Name: versioning
Version: 0.2.3
Summary: Python version sorting tool and MySQL version manager
Home-page: https://github.com/mjbrisebois/pyversioning
Author: Matthew Brisebois
Author-email: matthew@webheroes.ca
License: UNKNOWN
Keywords: pyversioning,versioning,version,version sorting,mysql version,mysql
Platform: UNKNOWN
